pfhedge/__init__.py
pfhedge/_utils/__init__.py
pfhedge/_utils/bisect.py
pfhedge/_utils/doc.py
pfhedge/_utils/hook.py
pfhedge/_utils/lazy.py
pfhedge/_utils/operations.py
pfhedge/_utils/parse.py
pfhedge/_utils/str.py
pfhedge/_utils/testing.py
pfhedge/_utils/typing.py
pfhedge/autogreek.py
pfhedge/features/__init__.py
pfhedge/features/_base.py
pfhedge/features/_getter.py
pfhedge/features/container.py
pfhedge/features/features.py
pfhedge/instruments/__init__.py
pfhedge/instruments/base.py
pfhedge/instruments/derivative/__init__.py
pfhedge/instruments/derivative/american_binary.py
pfhedge/instruments/derivative/base.py
pfhedge/instruments/derivative/cliquet.py
pfhedge/instruments/derivative/european.py
pfhedge/instruments/derivative/european_binary.py
pfhedge/instruments/derivative/lookback.py
pfhedge/instruments/derivative/variance_swap.py
pfhedge/instruments/primary/__init__.py
pfhedge/instruments/primary/base.py
pfhedge/instruments/primary/brownian.py
pfhedge/instruments/primary/cir.py
pfhedge/instruments/primary/heston.py
pfhedge/instruments/primary/kou_jump.py
pfhedge/instruments/primary/local_volatility.py
pfhedge/instruments/primary/merton_jump.py
pfhedge/instruments/primary/rough_bergomi.py
pfhedge/instruments/primary/vasicek.py
pfhedge/nn/__init__.py
pfhedge/nn/functional.py
pfhedge/nn/modules/__init__.py
pfhedge/nn/modules/bs/__init__.py
pfhedge/nn/modules/bs/_base.py
pfhedge/nn/modules/bs/american_binary.py
pfhedge/nn/modules/bs/black_scholes.py
pfhedge/nn/modules/bs/european.py
pfhedge/nn/modules/bs/european_binary.py
pfhedge/nn/modules/bs/lookback.py
pfhedge/nn/modules/clamp.py
pfhedge/nn/modules/hedger.py
pfhedge/nn/modules/loss.py
pfhedge/nn/modules/mlp.py
pfhedge/nn/modules/naked.py
pfhedge/nn/modules/svi.py
pfhedge/nn/modules/ww.py
pfhedge/stochastic/__init__.py
pfhedge/stochastic/_utils.py
pfhedge/stochastic/brownian.py
pfhedge/stochastic/cir.py
pfhedge/stochastic/engine.py
pfhedge/stochastic/heston.py
pfhedge/stochastic/kou_jump.py
pfhedge-0.23.0.dist-info/LICENSE
pfhedge-0.23.0.dist-info/METADATA
pfhedge-0.23.0.dist-info/WHEEL
pfhedge-0.23.0.dist-info/RECORD
